{"641120": [1485, 1514, 1475, "Abbey, Anate"], "6414842": [0, 0, 0, "Abreu Gonzalez, Michael Joan"], "6416713": [0, 0, 0, "Abreu Rodriguez, Aaron Ivan"], "6414834": [0, 0, 1692, "Abreu, Maykel Junior"], "6417043": [1660, 0, 0, "Acero Alcantara, Eslokaren"], "6412491": [0, 0, 1812, "Acevedo, Angel"], "6412939": [0, 0, 0, "Acevedo, Fausto"], "6412947": [0, 0, 0, "Acevedo, Franberli"], "6412505": [0, 0, 0, "Acevedo, Miguel"], "6410090": [0, 0, 0, "Acevedo, Santiago"], "641138": [2003, 2007, 0, "Achereiner, Guillaume"], "6413579": [0, 0, 0, "Acosta De Jesus, Maria Altagracia"], "6417167": [1879, 0, 0, "Acosta, Manuel De Jesus"], "6412092": [0, 0, 0, "Acosta, Maria Altagracia"], "6412513": [0, 1753, 0, "Acosta, Orlando"], "641847": [2020, 1968, 0, "Acquart, Alexis"], "641146": [1969, 0, 1928, "Acquart, Laurent"], "641871": [1900, 0, 0, "Aggoune, Eddy"], "6413064": [1792, 0, 0, "Agramonte Ramirez, Jorge Luis"], "6412157": [0, 0, 0, "Alberti, Toni"], "6413595": [0, 0, 0, "Alberto, Isaias"], "6410383": [0, 0, 1968, "Albuelme Garcia, Ahimelec Ediberto"], "6419674": [0, 0, 0, "Alcantara Hernandez , Pedro Anto"], "6419771": [1862, 0, 1921, "Alcantara Marte, Joan Marcelino"], "6417329": [1929, 0, 0, "Alcantara Matos, Digno Jose"], "6417337": [0, 0, 0, "Alcantara, Frandioly"], "6417345": [0, 0, 0, "Alcantara, Jose Arturo"], "6414532": [0, 0, 0, "Alcantara, Turbi"], "6413072": [0, 0, 0, "Alexander, Bruno"], "6416845": [1803, 0, 1805, "Alfau Sencion, Lisbeth"], "641154": [1917, 0, 0, "Algaba, Solene"], "641162": [1868, 1774, 0, "Allemand, Christian"], "6414290": [0, 0, 0, "Almanzar Canario, Aristides"], "6411517": [1875, 0, 1887, "Almanzar Flores, Pedro Manuel"], "6418198": [0, 0, 0, "Almanzar Ramos, Raquel M."], "6418856": [0, 0, 0, "Almanzar Reyes, Moises"], "6417612": [0, 0, 0, "Almonte Barrera, Jonas"], "6418899": [0, 0, 0, "Almonte G., Morel"], "6417175": [0, 0, 0, "Almonte Gutierrez, Hector Manuel"], "6416543": [0, 0, 0, "Almonte Salcedo, Felipe"], "6415725": [0, 1647, 1763, "Almonte, Henrry Nicolas"], "6415482": [0, 0, 0, "Almonte, Janise"], "6411657": [0, 0, 0, "Almonte, Wascar"], "6411665": [0, 0, 0, "Almonte, Welinton"], "6411010": [0, 0, 0, "Almonte, Yoel"], "6416438": [0, 0, 0, "Alonso Padua, Alejandro"], "6410588": [0, 0, 1857, "Alonzo Pujols, Michael"], "6419666": [1927, 0, 0, "Alvarez Leger, Angel Maria"], "6414125": [0, 0, 0, "Alvarez, Frederic Manuel"], "6419070": [0, 0, 0, "Amador , Rafael"], "6415105": [0, 0, 0, "Amador Blanco, Richard Alexander"], "6412521": [1899, 0, 1901, "Amparo, Edwin"], "6418520": [0, 0, 0, "Anazco Huaraya, Reynaldo Carmelo"], "6419186": [0, 0, 0, "Andujar , Kirsy"], "6416381": [0, 0, 0, "Andujar Baez, Maria Isabel"], "6412343": [0, 0, 0, "Andujar, Thomas"], "6419739": [0, 0, 0, "Angel Montilla, Juan Thomas"], "6411525": [0, 0, 0, "Antidor De La Cru, Selito Eduard"], "6413340": [0, 0, 0, "Antigua Diaz, Angel"], "6418201": [0, 0, 0, "Apolinar De Lanoy, Marlyn M."], "6416144": [0, 0, 0, "Aponte Hernandez, Jose Adolfo"], "6411649": [0, 0, 0, "Aquiles Rodriguez Salcedo"], "6417906": [0, 0, 0, "Aquiles, Saul"], "6415547": [1719, 0, 1680, "Aquino Castillo, Leonardo"], "6412955": [0, 0, 0, "Aquino Pineda, Edison Samuel"], "6410804": [0, 0, 0, "Aquino, Euri"], "6412963": [1815, 0, 1813, "Aquino, Lenny"], "6411789": [0, 0, 0, "Aquino, Reyssi"], "6416241": [0, 0, 0, "Aracenas, Manuel"], "6416896": [2319, 2239, 2418, "Araujo Sanchez, Josue"], "6413609": [0, 0, 0, "Arciniega, Placido"], "641880": [1781, 1830, 0, "Arcusa, Michel"], "6417914": [0, 0, 0, "Arias Adom, Juan Carlos"], "6419259": [0, 0, 0, "Arias Feliz, Aslhyna"], "6417183": [0, 0, 0, "Arias Fernandez, Savier Humberto"], "6416721": [0, 0, 0, "Arias, Dante Jose"], "6419550": [0, 0, 1853, "Arias, Nelson"], "6415393": [0, 0, 0, "Arias, Oliver"], "6417434": [0, 0, 0, "Arias, Saviel"], "6414028": [0, 0, 0, "Arredondo Reyes, Jhann Carlos"], "6412530": [0, 0, 0, "Arthur, Manolo"], "641170": [1965, 0, 0, "Asensio, Frederic"], "6419194": [0, 0, 0, "Asuncion , Richard"], "641901": [1715, 1762, 0, "Auge, Jean"], "6413080": [0, 0, 0, "Augusto, Angeisi"], "6411029": [0, 0, 1843, "Aybar Mancebo, Jose"], "6413099": [0, 0, 0, "Aybar, Bryan Alexander"], "641910": [1791, 1786, 0, "Baches, Frederic"], "6416250": [1774, 0, 0, "Baez Fondeur, Maximo Bolivar"], "6418643": [0, 0, 0, "Baez Jimenez, Francisco Alberto"], "6411290": [0, 0, 0, "Baez, Junior"], "641928": [1833, 1813, 0, "Balais, Andre"], "6416268": [0, 0, 0, "Baldera, Gregorio"], "6419089": [0, 0, 0, "Bancalari, Juan Jose"], "641189": [1998, 0, 0, "Baranger, Marc"], "641936": [2073, 0, 0, "Barbot, Pascal"], "6419569": [0, 0, 1735, "Barcalari, Juan Jose"], "641944": [2095, 0, 0, "Bardin, Xavier"], "6410057": [1822, 0, 0, "Barias Aquino, Tomas"], "6415180": [0, 0, 0, "Barias Florentino, Juan Thomas"], "6416900": [0, 0, 0, "Barias Florentino, Melody"], "641952": [2222, 2138, 2205, "Baron, Thierry"], "641979": [1896, 0, 0, "Bastide, Bernard"], "6416276": [1843, 0, 1843, "Batista Crispin, Kenny Leonardo"], "6416730": [1705, 1723, 0, "Batista Serrano, Angel Yuliano"], "6412548": [0, 0, 0, "Batista, Alex"], "6417540": [0, 0, 0, "Batista, Darlin Alexander"], "641987": [2001, 1998, 0, "Baumann, Benjamin"], "6418902": [0, 0, 0, "Baundier Tamer , Luis Miguel"], "6416918": [0, 0, 0, "Bautista Gonzalez, Juan"], "6416489": [0, 0, 0, "Bautista Lugo, Omar Ambioris"], "6418210": [1540, 0, 0, "Bautista, Angelica"], "6417620": [0, 0, 0, "Belen , Yomaili Virgi"], "6419356": [0, 0, 0, "Belen Reyes, Leslie"], "641197": [1914, 1900, 0, "Bellay, Philippe"], "6417353": [1825, 0, 1835, "Bello Herrera, Darwin Smith"], "6414303": [0, 0, 0, "Bello Reyes, Donal"], "6411037": [0, 0, 0, "Bello, Bryan"], "6411860": [0, 0, 0, "Beltre, Alfredo Alonso"], "6410812": [0, 0, 0, "Beltre, Fausto"], "641995": [2056, 0, 0, "Ben Khelifa, Noomene"], "6415512": [1742, 0, 1699, "Bens de los Santos, Felix Jose"], "6418228": [0, 0, 0, "Beriguete, Arlenis"], "6412165": [0, 0, 0, "Berroa, Angel Miguel"], "6413102": [0, 0, 0, "Bido Frias, Jose"], "6410391": [0, 0, 0, "Bigay, Nelson"], "6415636": [0, 0, 0, "Blonden, Juan Carlos"], "6417922": [0, 0, 0, "Bolivar, Johery"], "6415067": [0, 0, 0, "Borbon, Wilson"], "641219": [1825, 0, 0, "Bouzin, Igor"], "6414850": [1797, 0, 1807, "Brea Herrera, Hector Paul"], "6411878": [0, 0, 0, "Brea Nunez, Wailan Daniel"], "641227": [1858, 0, 0, "Bresard, Isabelle"], "6410405": [0, 0, 0, "Breton Rivas, Francibel"], "6418651": [0, 0, 0, "Brito Burgos, Liyewry"], "6418660": [0, 0, 0, "Brito Mercedes, Blas"], "6419402": [1800, 0, 1840, "Brito Nunez, Angel Manuel"], "6418678": [0, 0, 0, "Brito Nunez, Marisol"], "6418686": [0, 0, 0, "Brito Nunez, Perla Massiel"], "6418694": [0, 0, 0, "Brito Nunez, Sury Maria"], "6412556": [1894, 0, 1875, "Brito, Manuel Angel"], "6414540": [0, 0, 0, "Bruno, Alex"], "641235": [1811, 1886, 1820, "Budin, Florent"], "6416926": [1780, 0, 1830, "Bueno, Francisco Joel"], "6411045": [0, 0, 0, "Bujosa, Alex"], "6411053": [0, 0, 0, "Bujosa, David"], "641243": [1886, 0, 0, "Bulcourt, Nicolas"], "6416934": [1743, 0, 0, "Burgos Castro, Jose Ramon"], "6414311": [0, 0, 0, "Burgos, Fatima"], "6417639": [0, 0, 1731, "Burgos, Jhoan"], "641251": [1729, 0, 0, "Bussani, Patrick"], "6416284": [0, 0, 0, "Cabreja Lora, Manuel De Jesus"], "6416292": [1742, 0, 0, "Cabreja Lora, Suzette"], "6410774": [0, 0, 2082, "Cabrera, Fernando"], "6412564": [0, 0, 0, "Cabrera, Jose Alfonso"], "6414559": [0, 0, 1925, "Cabrera, Reyi"], "6415415": [0, 0, 0, "Cadet, Ismael"], "6417930": [0, 0, 0, "Calderon De Luna, Brandy Leydy"], "6410170": [0, 0, 0, "Calderon Espiritu, Guillermo"], "6417000": [0, 0, 0, "Calderon Mejia , Erika"], "6417019": [1706, 0, 0, "Calderon Mejia, Yokaury"], "6411673": [1686, 0, 0, "Camacho Rosario, Cristal"], "6410820": [0, 0, 0, "Campusano, Pablo"], "6417060": [0, 0, 0, "Capellan Santana, Jairo"], "6410839": [0, 0, 0, "Caraballo, Antonio"], "6414923": [0, 0, 0, "Caraballo, Enmanuel"], "6418708": [1807, 0, 0, "Carderon Gonzalez, Josue Eliesez"], "6410421": [0, 0, 0, "Carlos, Jary"], "6413331": [1870, 0, 1845, "Carmona, Samuel Ismael"], "6417949": [0, 0, 0, "Carpio Espinal, Marvin Orobys"], "6416551": [0, 0, 1967, "Carrasco Medina, Federico Paulino"], "6411886": [0, 0, 0, "Carter, Theogene"], "6411894": [0, 0, 0, "Casilla Reyes, Augusto Edgardo"], "6418716": [0, 0, 0, "Castillo Alvarez, Albert"], "6413498": [0, 0, 0, "Castillo Marte, Wilton Leonardo"], "6412106": [1909, 0, 1886, "Castillo Pena, Patricia Evarista"], "6417825": [0, 0, 0, "Castillo Santos, Fraylin Ramon"], "6412572": [0, 0, 0, "Castillo, Gerson"], "6411681": [0, 0, 0, "Castillo, Yordenis"], "6415830": [0, 0, 1805, "Castro Brito, Rafael"], "6419968": [0, 0, 0, "Castro Brito, Rafael"], "6412890": [1715, 0, 0, "Castro Fernandez, Domingo"], "6419976": [0, 0, 1855, "Castro Grullon, Rafael"], "6419615": [0, 0, 0, "Castro Martinez, Angel"], "6419810": [0, 0, 1711, "Cedeno Castro, Jose"], "6414320": [1906, 0, 1927, "Cepeda De Jesus, Renny Saul"], "6419364": [0, 0, 0, "Cepeda De La Rosa, Darleni"], "6415946": [0, 0, 0, "Cerda, Carlos"], "6414877": [0, 0, 0, "Cespedes, Elvis Jose"], "6414133": [0, 0, 0, "Chala Arias, Adoni Manuel"], "6415113": [0, 0, 0, "Chala Arias, David"], "6414141": [1792, 0, 1757, "Chalas Arias, Teudy Anthony"], "641286": [1759, 0, 0, "Chandran, Franck"], "641294": [1916, 1937, 0, "Chaumont, Adeline"], "641308": [1885, 0, 0, "Chochoy, Nicolas"], "6417647": [0, 0, 0, "Clemente Rosario, Felix Confesor"], "6414338": [0, 0, 0, "Clemente Santos, Eyron"], "6413617": [0, 0, 0, "Collado E., Joel"], "6410847": [1907, 0, 2056, "Collado Guzman, Juan Danilo"], "6413625": [0, 0, 0, "Collado, Ahtolin"], "6413587": [0, 0, 0, "Concepcion, Alba Nelis"], "6411690": [0, 0, 0, "Concepcion, Raimyn"], "6419534": [0, 0, 0, "Consoro Soriano, Raudis Medrian"], "6410189": [0, 0, 0, "Contreras Contreras, Martires"], "6419410": [0, 0, 0, "Contreras Santana, Branyel Jose"], "6419429": [0, 0, 0, "Cordero Diaz, Alexander Isaac"], "6419437": [0, 0, 0, "Cordero Diaz, Halen Noel"], "6412971": [0, 0, 0, "Cordero, Luis Alberto"], "6414567": [0, 0, 0, "Cornelio Brito, Omar"], "6413110": [0, 0, 0, "Cornelio, Onetty"], "6419984": [0, 0, 1704, "Cornielle Pons, Reyes Gerobohan"], "6419747": [0, 0, 1707, "Coronado Reyes, Nicholes Ramon"], "6412580": [0, 0, 0, "Coronado Vargas, Santo Cosme"], "6415474": [1824, 0, 0, "Corporan Alcala, Paola Melissa"], "6417655": [0, 0, 0, "Corsino , Lowis"], "6414346": [0, 0, 0, "Cortorreal Hernandez, Oscairy"], "6419631": [1773, 0, 0, "Cortorreal Severino, Raynier Ant"], "6411541": [0, 0, 0, "Cruz Cruceta, Francisco Gabriel"], "6416454": [0, 0, 0, "Cruz De Los Santos, Rolando"], "6414036": [1835, 0, 0, "Cruz Fernandez, Johan"], "6410197": [1785, 0, 1782, "Cruz Jimenez, Gabriel"], "6418910": [0, 0, 0, "Cruz Jr, Leonardo"], "6413633": [0, 0, 0, "Cruz Victoriano, Elvin"], "6412173": [0, 0, 0, "Cruz, Joan"], "6416500": [0, 0, 0, "Cuduco Sanchez, Deivi Miguel A."], "6412823": [0, 0, 0, "Cuduco, Rafael"], "6417833": [0, 0, 0, "Cuello Monegro, Renan"], "6412181": [0, 0, 0, "Cuello, Tito"], "6419348": [1897, 0, 0, "Cuevas Feliz, Fernando Jose"], "6416470": [0, 0, 0, "Cuevas Ferreras, Ismael"], "6414931": [0, 0, 1771, "Cuevas Rosario, Marcelo"], "6419208": [0, 0, 1800, "Custodio Lara, Francis Esmaller"], "641316": [0, 0, 0, "Dalens, Jean-Jacques"], "6417191": [0, 0, 0, "Dalizie, Starly"], "6411061": [0, 0, 0, "David, Andres"], "6413900": [0, 0, 0, "De Beras, Michael"], "6415733": [1852, 0, 1812, "De Jesus Martinez, Enmanuel Olivo"], "6418538": [0, 0, 0, "De La Cruz Ayala, Franklin Alber"], "6414869": [1730, 0, 0, "De La Cruz Lugo, Rony Alberto"], "6411550": [0, 0, 0, "De La Cruz Reyes, Enmanuel"], "6416578": [0, 0, 1828, "De La Cruz Severino, Yegeurys"], "6417663": [0, 0, 0, "De La Cruz, Adriel Manuel"], "6419828": [0, 0, 1906, "De La Cruz, Hector Bienvenido"], "6415644": [0, 0, 1830, "De La Cruz, Jeison"], "6415857": [0, 0, 0, "De La Cruz, Jeorge Luis"], "6413919": [0, 0, 0, "De La Cruz, Reynaldo"], "6417078": [0, 0, 0, "De La Cruz, Yergeurys"], "6417671": [0, 0, 0, "De La Mota Garcia, Keifry Alexan"], "6419372": [0, 0, 0, "De La Rosa Pineda, Dirianny"], "6410430": [1849, 0, 1840, "De La Rosa Rodriguez, Isaias"], "6412599": [0, 0, 1912, "De La Rosa, Francisco"], "6411797": [0, 0, 0, "De La Rosa, Juan Damian"], "6413501": [0, 0, 0, "De Leon Dominguez, Junior Antoni"], "6410200": [1779, 0, 1794, "De Leon, Julio Cesar"], "6413641": [0, 0, 0, "De Leon, Ronny"], "6414150": [0, 0, 0, "De Los Santos , Jesus Manuel"], "6419321": [1926, 1866, 0, "De Los Santos Abad, Bryan"], "6412998": [1855, 0, 1846, "De Los Santos Loweski, Orlando"], "6417558": [0, 0, 0, "De Los Santos M., Juan Guillermo"], "6418635": [1885, 0, 0, "De Los Santos Munagorri, Juan"], "6412190": [0, 0, 0, "De Los Santos, Domingo"], "6416497": [0, 0, 0, "De Los Santos, Francisco Alberto"], "6412203": [0, 0, 0, "De Los Santos, Henry"], "6416942": [0, 0, 0, "De Los Santos, Ramon Felix"], "6417680": [0, 0, 0, "De Pena Reynoso, Enmanuel"], "6418414": [0, 0, 0, "Del Rosario , Martin"], "6417957": [0, 0, 0, "Del Rosario Polanco, Jance L."], "641324": [1910, 0, 0, "Delaitre, Frederic"], "641332": [1902, 0, 0, "Delinotte, Axelle"], "6416152": [0, 0, 1782, "Diaz Camilo, Angel Francisco"], "6415954": [1818, 0, 1806, "Diaz Rodriguez Wilber Manuel"], "6410456": [1957, 0, 1864, "Diaz Valdez, Eugenio Daniel"], "6412483": [1873, 0, 0, "Diaz Vicente, Huascar Jael"], "6418546": [1852, 0, 0, "Diaz Viloria, Maximo Alexander"], "6415741": [0, 0, 0, "Diaz Y Diaz, Ruddy Norberto"], "6417965": [0, 0, 0, "Diaz, Enmanuel Nicolas"], "6419216": [0, 0, 0, "Diaz, Gregori"], "6417442": [0, 0, 0, "Diaz, Isael"], "6414893": [0, 0, 0, "Diaz, Joaquin NO"], "6416748": [0, 0, 0, "Dominguez Acosta, Cristopher"], "6419755": [1731, 0, 0, "Dominguez Duran, Rabel Romarico"], "6414168": [0, 0, 0, "Dominguez, Deimi"], "6410464": [0, 0, 1932, "Dominguez, Richard Lorenzo"], "6414176": [0, 0, 0, "Dominguez, Wascar"], "6415423": [0, 0, 0, "Duberge Ulbaez, Alfonzo"], "641103": [1738, 0, 0, "Dufour, Jacques"], "6416993": [1940, 0, 0, "Duran Romero, Johnny Ismael"], "6417973": [0, 0, 0, "Duran, Enmanuel"], "6417450": [0, 0, 0, "Duran, Robin"], "641367": [1932, 0, 0, "Dureau, Laurent"], "641375": [1977, 1985, 1980, "Durez, Cedric"], "6414940": [0, 0, 0, "Duverge, Rolando"], "6416586": [0, 0, 0, "Eimer, Romero"], "6417051": [0, 0, 0, "Elmudesis, Ana Lucia"], "6418724": [0, 0, 0, "Encarnacion Brito, Genesis Maria"], "6414575": [0, 0, 0, "Encarnacion De Pena, Marcel Felipe"], "6417361": [0, 0, 0, "Encarnacion Ortiz, Manuel Enrriq"], "6411908": [0, 0, 0, "Encarnacion, Dalwin Alexander"], "6419291": [1746, 1740, 0, "Encarnacion, Keyner Vladimir"], "641383": [1592, 0, 0, "Engel, Gerard"], "6416160": [0, 0, 0, "Escoto Gomez, Eddy Antonio"], "6418422": [1760, 0, 0, "Espinal Geraldo, German Adalbert"], "6417981": [0, 0, 0, "Espinal, Franklin Enmanuel"], "6413927": [1905, 1894, 0, "Espinal, Virgilio Antonio"], "6414583": [0, 0, 0, "Espinosa, Alexander"], "6415466": [1726, 0, 0, "Estevez, Vianyelis Stephanie"], "6419836": [0, 0, 1783, "Eusebio Jimenez , Joel Alexander"], "6418236": [1597, 0, 0, "Familia Martinez, Yissel"], "6419844": [1852, 0, 1792, "Felipe Medina, Robert"], "6417990": [0, 0, 0, "Felipe Obispo, Erick Franther"], "6414958": [0, 0, 0, "Felix Reyes, Jailin"], "6413129": [0, 0, 0, "Felix, Soenny"], "6416560": [1858, 1881, 1944, "Feliz Custodio, Miguel Angel"], "6413137": [1816, 0, 0, "Feliz Gomez, Octavio Emmanuel"], "6415440": [0, 0, 0, "Feliz Reyes, Loyda Soribel"], "6411070": [1774, 0, 0, "Feliz Salazar, Karolay"], "6414966": [0, 0, 0, "Feliz, Brendy"], "6415431": [0, 0, 0, "Feliz, Esmaikel"], "6410103": [0, 0, 0, "Feliz, Juan E."], "6417205": [0, 0, 0, "Fermin, Arismendi"], "6418929": [0, 0, 0, "Fernandez , Pedro"], "6418490": [0, 0, 0, "Fernandez Cordero, Elianny"], "6411800": [0, 0, 0, "Fernandez Luciano, Juan Jose"], "6413005": [1870, 0, 1884, "Fernandez Polanco, Angel Miguel"], "6416888": [1897, 0, 0, "Fernandez Reyes, Roberto Elpidio"], "6413935": [0, 0, 0, "Fernandez, Aliem"], "6413145": [1917, 0, 1915, "Fernandez, Aliem Alayo"], "6417213": [0, 0, 0, "Fernandez, Dionicio"], "6415920": [0, 0, 0, "Fernandez, Roberto"], "6412211": [0, 0, 0, "Fernandez, Yerison"], "6412246": [1614, 0, 0, "Fernando Javier, Guerrero Gavilan"], "6419623": [1753, 0, 0, "Ferrando Mata, Jose Daniel"], "6416004": [2133, 0, 0, "Ferreira Fernandez, Sergio"], "6412386": [1786, 0, 0, "Ferreras, Felipe Neris"], "6410472": [0, 0, 1848, "Ferreras, Julio"], "6418007": [0, 0, 0, "Figueroa De La Cruz, Eugenio J"], "6412602": [0, 0, 0, "Fischting, Leo"], "6415202": [0, 0, 0, "Florentino Suero, Emilio"], "6417698": [0, 0, 0, "Flores Garcia, Maria Vicmarling"], "6412220": [0, 0, 0, "Fontanillas Mancebo, Ricardo Alfonzo"], "641405": [2001, 1971, 0, "Forestier, Carole"], "6412610": [0, 0, 0, "Francisco, Fausto"], "6415385": [1812, 0, 1816, "Franco Valenzuela, Albaro"], "6419224": [0, 0, 0, "Franjul, Arturo"], "641413": [0, 0, 0, "Fredoueil, Olivier"], "6419577": [0, 0, 1959, "Frias Arciniega, Cristobal"], "6417221": [1812, 1811, 1766, "Frias Rijo, Leonelbi"], "6412831": [0, 0, 0, "Frias, Juan Carlos"], "6410480": [0, 0, 1788, "Galva Montero, Eusebio"], "6418937": [0, 0, 0, "Garcia , Franklin"], "6419100": [1935, 0, 1816, "Garcia Florentino, Hector"], "6418554": [0, 0, 0, "Garcia Hichez, Waldy Raymundo"], "6414362": [0, 0, 0, "Garcia Matias, Charlys"], "6415210": [1796, 0, 0, "Garcia Matos, Rafael Leonidas"], "6417701": [0, 0, 0, "Garcia Pena, Darling Antony"], "6417710": [0, 0, 0, "Garcia Pena, Deidy Altagracia"], "6417728": [0, 0, 0, "Garcia Pena, Kerbi Antony"], "6417736": [0, 0, 0, "Garcia Pena, Maria Marlene"], "6411703": [1772, 0, 1779, "Garcia Robles, Rafael Antonio"], "6415229": [0, 0, 0, "Garcia Santos, Domingo Andres"], "6415555": [0, 0, 0, "Garcia, Alfredo NA"], "6411088": [0, 0, 0, "Garcia, Dahansen"], "6417230": [0, 0, 0, "Garcia, Joel"], "6416950": [0, 0, 0, "Garcia, Juan Antonio"], "6413650": [0, 0, 0, "Garcia, Manuel name match"], "6412394": [0, 0, 0, "Garcia, Miguel N"], "6419852": [0, 0, 1788, "Garo Castro, Emil"], "641421": [1948, 0, 0, "Gengoul, Thierry"], "6418503": [1639, 0, 0, "Gerardino Rosario, Clairelina"], "6413366": [0, 0, 2038, "Germes Suarez, Hector Augusto"], "6414370": [1968, 0, 0, "Gil Bonilla, Eritoniel"], "6413510": [0, 0, 0, "Gil Compres, Johnattan Alexander"], "6417841": [0, 0, 0, "Gil Villa, Frandy Enmanuel"], "6418244": [0, 0, 0, "Gil, Maria Alejandra"], "6419860": [0, 0, 1819, "Giraldi , Fernando"], "641448": [1987, 0, 0, "Godel, Wenceslas"], "6419453": [1684, 0, 1664, "Goicochea Ramirez, Demetrio Manu"], "6410219": [1884, 0, 1879, "Gomez Batista, Eduardo Antonio"], "6418732": [1738, 0, 1763, "Gomez Brito, Wander"], "6419119": [0, 0, 1710, "Gomez Garcia, Rafael De Jesus"], "6414591": [0, 0, 1783, "Gomez Popoters, Victor Ramon"], "6414974": [0, 0, 0, "Gomez Santana, Reilin"], "6413951": [0, 0, 0, "Gomez, Angeisi"], "6416306": [0, 0, 0, "Gomez, Isidro"], "6416314": [0, 0, 0, "Gomez, Juan Francisco"], "6413382": [0, 0, 1925, "Gomez, Manolo"], "6415563": [0, 0, 0, "Gomez, Marcio"], "6416322": [0, 0, 0, "Gomez, Ramon"], "6418252": [0, 0, 0, "Gomez, Ruby Marcelle"], "6411096": [0, 0, 0, "Gonzalez  Nunez, Merciades Cesareo"], "6418562": [1770, 0, 0, "Gonzalez Abreu, Neulyn"], "6418511": [0, 0, 0, "Gonzalez Acosta, Yocaira"], "6418260": [0, 0, 0, "Gonzalez M., Maria Indiana"], "6411320": [1734, 0, 0, "Gonzalez Robles, Nespil Yusel"], "6416179": [0, 0, 1802, "Gonzalez Taveras, Joel Ramon Dav"], "6416187": [0, 0, 0, "Gonzalez Taveras, Jose Maria"], "6412238": [0, 0, 0, "Gonzalez, Alfonso"], "6415750": [0, 0, 0, "Gonzalez, Claudio Argenis"], "6412629": [0, 0, 0, "Gonzalez, David P."], "6419640": [0, 0, 0, "Gonzalez, Engels"], "6416594": [0, 0, 0, "Gonzalez, Jose NO COMPLETO"], "6413153": [0, 0, 0, "Gonzalez, Juan Bautista"], "6413668": [0, 0, 0, "Gonzalez, Marcos A name match"], "6416012": [1932, 1939, 1876, "Gonzalez, Pablo Jose"], "6413676": [0, 0, 0, "Gonzalez, Savier"], "6412840": [0, 0, 0, "Gonzalez, William"], "641456": [1846, 0, 0, "Grateau, Jean-Noel"], "6412408": [0, 0, 0, "Grullon, Radhames"], "6411339": [1773, 0, 0, "Guaba Vasquez, Francisco Antonio"], "6415962": [1770, 0, 0, "Guaba, Alejandro"], "6415865": [0, 0, 0, "Guaba, Pedro"], "6419879": [0, 0, 1766, "Guerrero Castillo, Fernando"], "6410863": [0, 0, 0, "Guerrero, Jose Alejandro"], "641464": [2136, 2036, 0, "Guignier, Nicolas"], "6419275": [0, 0, 0, "Gutierrez Rosado, Jhons Felix"], "6416020": [1610, 0, 1633, "Gutierrez, Mario Alejandro"], "6415245": [0, 0, 0, "Guzman Cruz, Miguel Angel"], "6418279": [0, 0, 0, "Guzman Herrera, Jordannia"], "6418287": [0, 0, 0, "Guzman, Doribel"], "6415075": [0, 0, 0, "Guzman, Jose Gregorio"], "6413161": [0, 0, 0, "Guzman, Karilin"], "6416608": [0, 0, 0, "Guzman, Marcelo"], "6413960": [1735, 0, 0, "Hache Santana, Jeorge Abraham"], "6419887": [0, 0, 0, "Hasbun Vigil, Daniel"], "6419895": [0, 0, 0, "Hasbun Vigil, Erick"], "641472": [1942, 0, 0, "Helmlinger, Thomas"], "6414389": [0, 0, 0, "Henriquez, Virgilio"], "6415571": [0, 0, 0, "Henrriquez Perez, Jose"], "641480": [1883, 1935, 1914, "Hentzen, Fabrice"], "6416039": [1916, 0, 1936, "Heredia Severino, George Matias"], "6418945": [0, 0, 0, "Hernandez , Jorge Luis"], "6415580": [0, 0, 0, "Hernandez H., Rafael Antonio"], "6419909": [0, 0, 0, "Hernandez Hernandez, Rafael"], "6418953": [0, 0, 0, "Hernandez Herrera, Luis Rafael"], "6413170": [0, 0, 0, "Hernandez Leyba, Julio Isaias"], "6417850": [0, 0, 0, "Hernandez Martinez, Ricardo"], "6418740": [0, 0, 0, "Hernandez Morel, Francisco Jesus"], "6413528": [1929, 0, 1987, "Hernandez Morel, Romel Antonio"], "6419232": [0, 0, 0, "Herrera Castillo, Luis"], "6417370": [1676, 0, 0, "Herrera Cepeda, Jose Alfonso"], "6413188": [0, 0, 1857, "Herrera Febles, Franklin"], "6413390": [0, 0, 0, "Herrera Herrera, Eliezer"], "6414605": [0, 0, 0, "Herrera Morillo, Jose Antonio"], "6417388": [0, 0, 0, "Herrera Taveras, Wander"], "6418759": [0, 0, 0, "Herrera Zapata, Francisco Antoni"], "6411819": [0, 0, 0, "Herrera, Melciades"], "6410871": [0, 0, 0, "Herrera, Starlin"], "6416195": [0, 0, 0, "Hidalgo Santos, Ariel"], "6411100": [0, 0, 0, "Hidalgo, Maria"], "6411118": [0, 0, 0, "Hidalgo, Miguel"], "6412645": [0, 0, 2127, "Hilario, Estarlin Manuel"], "6418767": [0, 0, 0, "Hinojosa, Jose Luis"], "6415873": [0, 0, 1853, "Holguin Castillo, Heriberto"], "6411347": [0, 0, 0, "Holguin, Edy Rafael"], "6417027": [0, 0, 0, "Inojosa, Xiomara"], "6419585": [0, 0, 1822, "Isaac, Jesus Alberto"], "6414184": [0, 0, 0, "Isabel, Adonis"], "6415148": [1837, 0, 0, "Izquierdo Martinez, Rafael Gerar"], "6412114": [0, 0, 0, "Jaquez Pimentel, Rocio Nicole"], "6417086": [1874, 0, 1908, "Javier Brito, Anudis"], "6414613": [1905, 0, 0, "Javier Florencio, Rafael Apolina"], "6416047": [1830, 0, 1828, "Jimenes, Luis Alberto"], "6411851": [0, 0, 0, "Jimenez Aguasvivas, Rafael D."], "6418864": [0, 0, 0, "Jimenez Burdiez, Luis Jose"], "6415253": [2213, 2145, 2162, "Jimenez Jimenez, Leandro"], "6416756": [0, 0, 0, "Jimenez Jorge, Arnaldo Daniel"], "6411126": [1890, 1948, 1984, "Jimenez Matos, Jimmy"], "6415490": [0, 0, 0, "Jimenez Medina, Laura Violeta"], "6418775": [0, 0, 0, "Jimenez Moronta, Anderson"], "6417744": [0, 0, 0, "Jimenez Valerio, Darwing Enmanue"], "6414907": [0, 0, 0, "Jimenez, Absalon"], "6410499": [0, 0, 1932, "Jimenez, Jason"], "6419127": [0, 0, 1888, "Jimenez, Luis Alberto"], "6419917": [0, 0, 0, "Jimenez, Yason"], "6415598": [0, 0, 0, "Joa, Francisco"], "6411711": [0, 0, 0, "Joaquin Labourd, Ricardo"], "6418015": [0, 0, 0, "Jorge, Jean"], "6411134": [0, 0, 0, "Jose, Geremy"], "6412653": [0, 0, 0, "Juma Samuel, Ruben"], "6414630": [0, 0, 0, "Junior, Lopez"], "6419461": [1984, 1930, 1898, "King Rodriguez, Os Misael"], "6419470": [1913, 1912, 1954, "King Soriano, Misael"], "641510": [1818, 1983, 1789, "Kvashyna, Tetyana"], "641529": [1990, 1952, 1866, "L'hermitte, Emmanuel"], "6415601": [0, 0, 0, "Landron Silverio, Wanny Rafael"], "6412459": [0, 0, 0, "Lantigua, Elvia"], "6414397": [0, 0, 0, "Lantigua, Hector Rodriguez"], "6414192": [0, 0, 0, "Lara, Abad"], "6418295": [0, 0, 0, "Lara, Angelica Cesarina"], "6415261": [0, 0, 0, "Lara, Basilio Heriberto"], "6417094": [0, 0, 1929, "Lara, Benito"], "6414206": [0, 0, 0, "Lara, Carlos Manuel"], "6414214": [0, 0, 1925, "Lara, Yeudy"], "6410502": [1990, 0, 1962, "Lazala Casso, Cesar Alfonso"], "6414982": [0, 0, 0, "Lazala, Ramon Elias"], "6414400": [0, 0, 0, "Lazaro, Marielsi"], "641537": [1574, 0, 0, "Le Coz, Yannick"], "641545": [1943, 0, 1954, "Le Franc, Yves"], "6412254": [0, 0, 0, "Lebron, Perez"], "6410510": [0, 0, 0, "Lebron, Raymon"], "641022": [0, 0, 0, "Leclercq, Alexandre"], "641030": [0, 0, 0, "Lecompte, Fabien"], "641049": [0, 0, 0, "Lecourt, Richard"], "641111": [1515, 0, 1455, "Leduc, Bruno"], "641200": [1680, 0, 0, "Lefeuvre, Emile"], "6410880": [0, 0, 0, "Legreaux Quintana, Manuel A."], "641260": [0, 0, 0, "Legros, Mikael"], "641278": [1770, 0, 0, "Lelarge, Franck"], "641340": [0, 0, 0, "Lemeille, Jean-marie"], "641812": [1992, 0, 0, "Lengert, Martin"], "6415806": [0, 0, 0, "Leonerdo Severino, Tania M."], "641553": [1882, 0, 0, "Lepagnol, Christian"], "641359": [0, 0, 0, "Leroux, Christophe"], "641391": [0, 0, 0, "Levray, Emmanuel"], "641430": [1819, 1773, 0, "Li, Zhigang"], "6417108": [0, 0, 0, "Linares Frias, Pedro Antonio"], "641499": [1639, 0, 0, "Liron, Roger"], "6418023": [0, 0, 0, "Lizardo Vargas, Gregory Nicolas"], "6416616": [1875, 0, 1956, "Lizardo, Carlos"], "641502": [1914, 1922, 1934, "Logerais, Pierre"], "641618": [0, 0, 0, "Lombard, Francois"], "641650": [0, 0, 0, "Lomonte, Christophe"], "641731": [0, 0, 0, "Long, Pierre"], "641740": [0, 0, 0, "Longepierre, Patrick"], "6415121": [1941, 0, 0, "Lopez Cruz, Sammy Aris"], "6417868": [0, 0, 0, "Lopez Hernandez, Juan Ysidro"], "6414990": [0, 0, 0, "Lopez Mallen , Bidenny"], "6415407": [0, 0, 0, "Lopez Mallen, Nelsi Maria"], "6417248": [0, 0, 0, "Lopez, Andrez"], "6413412": [0, 0, 0, "Lopez, Biddenny"], "6418031": [0, 0, 0, "Lopez, Gabriel Vilorio"], "6416624": [0, 0, 0, "Lopez, Jancito"], "6417469": [0, 0, 0, "Lopez, Pedro Manuel"], "6411487": [0, 0, 1935, "Lorenzo, David"], "641758": [0, 0, 0, "Louisy, Denis"], "6412858": [0, 0, 0, "Lowensky Lara, Wilman"], "6416632": [0, 0, 0, "Lugo Duran, Joel"], "6411843": [0, 0, 0, "Lulo, Mario"], "6418309": [0, 0, 0, "Luperon, Leonidas"], "641766": [0, 0, 0, "Luu, Boris"], "6418040": [0, 0, 0, "Luuberes, Starlin J."], "641790": [1796, 0, 0, "Ly, Marcel"], "641804": [1813, 0, 0, "L`huillier, Jean-marc"], "6418058": [0, 0, 0, "Mac Donald Sencion, Enrique"], "641839": [1789, 1699, 0, "Mace, Sebastien"], "641855": [1803, 1872, 0, "Magnier, Emmanuel"], "641863": [1452, 0, 0, "Maguer, Michel"], "641561": [2079, 2022, 0, "Mahiouz, Oualid"], "641570": [1912, 1934, 0, "Mahon, Vivien"], "641588": [1850, 0, 0, "Maillard, Julien"], "641898": [1693, 0, 0, "Maison, Jean-philippe"], "641960": [0, 0, 0, "Maizeroi, Vincent"], "6411142": [0, 0, 0, "Maldonado, Jefry"], "6417566": [0, 0, 2062, "Mariano Chevalier, Eugenio"], "641006": [1917, 1869, 0, "Marie, Laurent"], "6415768": [1911, 1890, 1860, "Marrero Garcia, Lendry Ismael"], "6417574": [0, 0, 0, "Marrero, Moises"], "6419925": [0, 0, 0, "Marrique, Geraldo"], "6414222": [1876, 0, 1872, "Marte Fermin, Johcrap"], "6417256": [0, 0, 0, "Marte Ovalle, Enye Jose"], "6413420": [0, 0, 1977, "Marte Perez, Yvan German"], "6418066": [0, 0, 1855, "Marte Quiroz, Adalberto Felix"], "6413536": [1863, 0, 1851, "Marte, Argelis Enmanuel"], "6414656": [0, 0, 0, "Marte, Johcraf"], "641596": [2123, 0, 0, "Martin, Cedric"], "641600": [1954, 0, 0, "Martin, Tristan"], "6417116": [0, 0, 2058, "Martinez Brito, Felix Jose"], "6415130": [0, 0, 0, "Martinez Casilla, Eugenio"], "6416055": [0, 0, 0, "Martinez De La Cruz, Pablo Frank"], "6416390": [0, 0, 0, "Martinez De La Santos, Katherine"], "6414419": [0, 0, 1773, "Martinez Estrella, Andres Ernesto"], "6410227": [1915, 1959, 1880, "Martinez Mateo, Arthur"], "6419488": [1891, 0, 1955, "Martinez Morel, Arismendy"], "6416519": [1622, 1639, 1575, "Martinez Pena, Victor"], "6412262": [0, 0, 1884, "Martinez Rijo, Miquea"], "6415270": [0, 0, 0, "Martinez Rojas, Rafael De Jesus"], "6418430": [0, 0, 1876, "Martinez Sanchez, Willy"], "6415881": [1884, 0, 1869, "Martinez Santana, Francis Amil"], "6411916": [1837, 0, 1860, "Martinez Vasquez, Reynaldo A."], "6414052": [0, 0, 0, "Martinez, Brayan"], "6413692": [0, 0, 0, "Martinez, Daniel name match"], "6418074": [0, 0, 0, "Martinez, Eliezer"], "6412351": [0, 0, 0, "Martinez, Gregorio Luciano"], "6414427": [0, 0, 0, "Martinez, I. Jerson"], "6410529": [0, 0, 0, "Martinez, Isaac"], "6416640": [0, 0, 0, "Martinez, Julio Cesar"], "6410537": [0, 0, 0, "Martinez, Miqueas"], "6416764": [0, 0, 0, "Martinez, Osvaldo"], "6413978": [0, 0, 0, "Martinez, Rafael name match"], "6413544": [0, 0, 0, "Martinez, Santos"], "6410545": [0, 0, 1762, "Mascarell, Jorge"], "6419135": [0, 0, 0, "Mateo Calderon, Juan Bautista"], "6413447": [0, 0, 0, "Mateo, Edward"], "6418961": [1848, 0, 1811, "Matias Galan, Milet"], "6414095": [0, 0, 0, "Matias, Nelson"], "6411150": [0, 0, 0, "Matos , Yamilet"], "6413455": [0, 0, 0, "Matos Brito, Leandro De Jesus"], "6416772": [0, 0, 0, "Matos Garcia, Leonis Fernando"], "6419496": [1899, 0, 1842, "Matos Guevara, Adan"], "6411576": [0, 0, 0, "Matos Nunez, Jose Daniel"], "6416969": [0, 0, 0, "Matos Santana, Abismael"], "6412416": [0, 0, 0, "Matos, Jose Maria"], "641626": [1860, 0, 0, "Mauget, Jean-Pierre"], "6413200": [0, 0, 0, "Mediavilla, Miguel"], "6415504": [0, 0, 0, "Medina Feliz, Erika Elizabeth"], "6418317": [0, 0, 0, "Medina Guzman, Jennifer M."], "6410553": [1822, 0, 0, "Medina Medina, Cesar Augusto"], "6410561": [1874, 0, 0, "Medina Medina, Freddy Alberto"], "6415520": [1851, 0, 1915, "Medina Moreta, Francisco A."], "6411924": [1894, 0, 0, "Medina Ramirez, Emilio"], "6413358": [0, 0, 0, "Medina Soler, Cesar Augusto"], "6410570": [0, 0, 0, "Medina, Sergio Alberto"], "6414060": [0, 0, 0, "Medina, Wilkin"], "6415008": [0, 0, 0, "Medina, Yerika"], "6419500": [0, 0, 0, "Mejia Guerrero, Lindo Jose"], "6412033": [1711, 0, 0, "Mejia Ricart, Tirso"], "6412122": [0, 0, 0, "Mejia Vargas, Alanna Michel"], "6417582": [0, 0, 0, "Mejia Vargas, Jhordin"], "6411584": [0, 0, 0, "Mejia Vargas, Juan Arturo"], "6410731": [0, 0, 0, "Mejia, Juan Jose"], "6419690": [2233, 2160, 2141, "Mendez Ramirez, Victor"], "6411827": [0, 0, 0, "Mendez Romero, Manuel Augusto"], "6411355": [0, 0, 0, "Mendez, Porfirio"], "6418325": [0, 0, 0, "Mercedes Acosta, Sor Ines"], "6418082": [0, 0, 0, "Mercedes M., Maximo Elias"], "6416853": [0, 0, 0, "Mercedes Terrero, Rafael"], "6419801": [0, 0, 1744, "Mercedes, Yeinfry"], "641634": [1720, 1783, 1799, "Mercier, Jean-Yves"], "641014": [1955, 0, 0, "Michaud, Jean-Noel"], "6414664": [0, 0, 0, "Michel, Tomas"], "6413463": [0, 0, 0, "Mieses Santos, Engel"], "6411932": [1839, 0, 0, "Mieses, Angel Domingo"], "641820": [1950, 0, 0, "Migne, Christophe"], "6415164": [0, 0, 0, "Mihailidis Lara, Basilio Heriber"], "6410065": [1854, 0, 1825, "Mileto, Nazzareno Pietro"], "6414672": [0, 0, 0, "Minaya, Anibal"], "6413552": [0, 0, 0, "Minier Rodriguez, Lendy"], "6414230": [0, 0, 0, "Minier, Hender"], "641669": [1558, 1546, 1546, "Mohammad Ghassemi, Vajieollah"], "6415199": [1845, 0, 0, "Mojica Castillo, Jose Manuel"], "6414680": [0, 0, 0, "Mojica, Alejandro"], "6418970": [0, 0, 0, "Moncion, Luis Ramon"], "6419593": [0, 0, 1804, "Monegro Santana, Willy Jhonatan"], "6410901": [0, 0, 0, "Montas, Manuel Moises"], "6412360": [0, 0, 0, "Montero Contreras, Erick"], "6414699": [0, 0, 1894, "Montero Suero, Rafael"], "6413021": [1702, 0, 0, "Montero, Joan Manuel"], "6416330": [0, 0, 1791, "Montero, Manuel"], "6410910": [0, 0, 1657, "Montes De Oca, Abel"], "6415296": [0, 0, 0, "Mora Martinez, Juana Rochelly"], "6418783": [0, 0, 0, "Mora Rosa, Wanderson"], "6415288": [0, 0, 0, "Mora, Juana Mercedes"], "6412661": [0, 0, 0, "Morales, Benjamin P."], "6415300": [0, 0, 0, "Moreta, Ivan"], "6417477": [1983, 0, 1917, "Morillo Monegro, Charvel"], "6410111": [0, 0, 1888, "Morillo, Esteban"], "6416403": [0, 0, 0, "Morillo, Iris Esmeralda"], "6415610": [0, 0, 0, "Morillo, Rene"], "6417752": [0, 0, 0, "Moronta, Miguel"], "6418988": [0, 0, 0, "Mosquea, Enrique"], "6414702": [0, 0, 0, "Mosquete, Carlos"], "6418449": [0, 0, 0, "Mota , Jose Arismendy"], "6413226": [0, 0, 0, "Munoz Melendez, Cristian Dimitri"], "6415318": [1898, 0, 0, "Munoz Salcedo, Mario"], "6410235": [1753, 0, 1767, "Munoz, Cristopher"], "6410073": [0, 0, 0, "Munoz, Mario T."], "641677": [1758, 0, 0, "Naveilhan, Roland"], "6414621": [1825, 0, 0, "Neris Jimenez, Alberto Rafael"], "6412670": [1978, 0, 2011, "Newman Caceres, Reynaldo Adolfo"], "6415032": [0, 0, 0, "Ng Leung, Sizeng"], "6415040": [0, 0, 0, "Ng Wu, John Ling"], "6410243": [2186, 0, 2086, "Nieto Rodriguez, Alejandro"], "6419283": [1693, 0, 0, "Nieves Espiritus Santos, Federic"], "6414249": [1891, 0, 1855, "Noboa , Marcos"], "6410251": [1865, 0, 1897, "Nouel Leon, Juan Manuel"], "6413234": [0, 0, 0, "Nova Ramirez, Eury"], "6412424": [0, 0, 0, "Nova, Francisco"], "6418570": [0, 0, 0, "Novas Gomez, Mario"], "6416780": [1883, 0, 1801, "Novas Gomez, Mario De Jesus"], "6416349": [1831, 0, 0, "Novas Novas, Andres Guillermo"], "6415652": [1896, 1927, 2034, "Nunez Astacio, Jose Miguel"], "6412688": [0, 0, 0, "Nunez Cid, Baldwin"], "6417876": [0, 0, 0, "Nunez Reinoso, Kelvin"], "6414257": [0, 0, 1853, "Nunez Reynoso, Angel"], "6413706": [0, 0, 0, "Nunez, Crisleidy"], "6413714": [0, 0, 0, "Nunez, Crismairy"], "6412696": [0, 0, 0, "Nunez, Garivaldi"], "6411940": [1653, 0, 0, "Olivero Calderon, Edwin"], "6417396": [0, 0, 0, "Orozco, Yorky"], "6419763": [1765, 0, 0, "Ortega Gonell, Ignacio Taciano"], "6411169": [1679, 0, 1726, "Ortiz Roman, Angello Mikhel"], "6415970": [0, 0, 0, "Ortiz, Alturo"], "6410260": [0, 0, 0, "Ortiz, Braison"], "6411363": [1803, 0, 1860, "Ortiz, Jose Arturo"], "6415679": [0, 0, 0, "Ortiz, Juan Jose"], "6411720": [0, 0, 0, "Ortiz, Luis A."], "6411177": [0, 0, 0, "Pacheco, Ciosmi"], "6412700": [0, 0, 0, "Padilla, Jorge"], "6410596": [0, 0, 0, "Palacio, Leo"], "6418333": [0, 0, 0, "Parache, Verenice"], "6411959": [1740, 0, 0, "Paredes Reyes, Pablo Francisco"], "6413722": [0, 0, 0, "Paredes, Arismendy"], "6413757": [0, 0, 0, "Paredes, Mario"], "6413730": [0, 0, 0, "Paredes, Yanleidy"], "6416799": [0, 0, 0, "Paso Docil, Jose Alfonso"], "6415814": [1797, 0, 0, "Paulino Hidalgo, Genesis"], "6416209": [0, 1923, 1901, "Paulino Jacobo, Ruby Manuel"], "6416217": [0, 0, 0, "Paulino Peralta, Juan Gabriel"], "6417132": [0, 0, 0, "Paulino Perez, Leonardo"], "6419143": [1961, 0, 1926, "Paulino Rijo, Luis Alejandro"], "6411371": [1817, 0, 1912, "Paulino Rosario, Dalver"], "6412718": [0, 0, 0, "Payano, Robinson"], "6412726": [0, 0, 0, "Pedegrin, Arturo"], "6418341": [0, 0, 0, "Peguero, Diana"], "6410600": [0, 0, 0, "Pena Cuello, Modesto Salomon"], "6418791": [0, 0, 0, "Pena Lopez, Andy Josue"], "6419704": [1858, 0, 1946, "Pena Marcano, Jose Carlos"], "6411967": [0, 0, 0, "Pena Rodriguez, Deusdedy"], "6416063": [0, 0, 0, "Pena Rodriguez, Luis Miguel"], "6413986": [1911, 1906, 1851, "Pena Sanchez, Raymundo Eduardo"], "6413765": [0, 0, 0, "Pena V., Alberto"], "6418996": [0, 0, 0, "Pena Vasquez , Yory Smith"], "6414435": [0, 0, 0, "Pena, Leonel"], "6419003": [0, 0, 0, "Peralta, Jose Genaro"], "6415822": [0, 0, 0, "Peralta, Shelly"], "6416659": [0, 0, 0, "Perdomo De Los Santo, Reynaldo"], "6416527": [0, 0, 0, "Perdomo Mejia, Stefani Alexandra"], "6418457": [1750, 0, 1786, "Perez Barcelo, Ricardo Antonio"], "6416071": [1595, 0, 1591, "Perez Cuevas, Henry Domingo"], "6418805": [0, 0, 0, "Perez De La Rosa, Angel Manuel"], "6419305": [0, 0, 0, "Perez Encarnacion, Kremly Federi"], "6410618": [1983, 0, 1927, "Perez Estevez, Bartolo"], "6416080": [1877, 0, 1870, "Perez Florentino, Yordan Nicolas"], "6410162": [0, 0, 0, "Perez Guzman, Vinicio Antonio"], "6414265": [0, 0, 0, "Perez Perez, Edwin"], "6419380": [0, 0, 0, "Perez Perez, Marialis"], "6415326": [0, 0, 0, "Perez, Cristino"], "6414710": [0, 0, 0, "Perez, David"], "6411398": [0, 0, 0, "Perez, Julian"], "6414729": [0, 0, 0, "Perez, Osvaldo"], "6412041": [0, 0, 0, "Pezoa Chahin, Fred Emyl"], "6411975": [0, 0, 0, "Pezoa, Fred"], "6411495": [0, 0, 0, "Piantini, Dario"], "6411592": [0, 0, 0, "Pichardo, Daris"], "6414745": [0, 0, 0, "Pimentel Nunez, Felix Manuel"], "6414737": [0, 0, 0, "Pimentel Rodriguez, Eduard Rafael"], "6413242": [0, 0, 0, "Pimentel, Fabio"], "6412734": [1893, 1910, 1909, "Plata, Rafael"], "641057": [0, 0, 0, "Plu, Arnaud"], "6413250": [0, 0, 2022, "Polanco De Oleo, Anderson"], "6417485": [0, 0, 0, "Polanco Lopez, Andrew"], "6416667": [1828, 0, 1829, "Polanco Rincon, Romer Alexander"], "6418090": [0, 0, 0, "Polanco, Alejandro Jaime"], "6410286": [0, 0, 1986, "Polanco, Arismendy"], "6418813": [0, 0, 0, "Portuondo Martinez, Benigno Ezeq"], "6417140": [0, 0, 0, "Potentini Rosario, Salvador Igna"], "6415334": [0, 0, 0, "Puello Salvador, Rebert Starlig"], "6412866": [0, 0, 0, "Puello, Bryan"], "6415687": [1936, 0, 0, "Puello, Pedro E."], "6416098": [1851, 0, 0, "Quezada Guzman, Samuel"], "6418589": [0, 0, 0, "Quezada Ortiz, Ramon"], "641685": [1893, 1989, 1965, "Rachez, Christophe"], "6413269": [0, 0, 0, "Ramirez Calderon, Gerrald"], "6418350": [1699, 0, 0, "Ramirez Jimenez, Geraldina Rafaela"], "6415660": [0, 0, 0, "Ramirez Nunez, Henry Miguel"], "6419399": [0, 0, 0, "Ramirez Rosso, Dayrobel"], "6419445": [0, 0, 0, "Ramirez Santana, Angel Grabiel"], "6417400": [0, 0, 0, "Ramirez, Abrahan"], "6410626": [1699, 0, 1775, "Ramirez, Deyvis"], "6412050": [0, 0, 0, "Ramirez, Tomas P."], "6410146": [1867, 0, 1840, "Ramos Burgos, Gregory Joel"], "6415989": [1783, 0, 0, "Ramos Guzman, Alvaro Luis"], "6419151": [1873, 0, 1866, "Ramos Martinez, Daminiel"], "6413773": [0, 0, 0, "Ramos, Casimiro"], "6413781": [0, 0, 0, "Ramos, Erika"], "6413790": [0, 0, 1710, "Ramos, Jose Raul"], "6413803": [0, 0, 0, "Ramos, Julian"], "6410740": [0, 0, 0, "Ravelo, Hector"], "6416977": [0, 0, 0, "Regalado, Alfredo"], "6414079": [0, 0, 0, "Respreto, Jose"], "6413811": [0, 0, 0, "Restituyo, Luis"], "6413820": [0, 0, 0, "Restituyo, Orlando"], "6418104": [0, 0, 0, "Restrepo I., Jose Isaac"], "6412068": [0, 0, 0, "Reyes Ariza, Erick Javier"], "6412130": [1533, 0, 0, "Reyes Bello, Daneiris"], "6410634": [2058, 0, 2098, "Reyes Capellan, Elby"], "6414443": [0, 0, 0, "Reyes Liranzo, Maximo"], "6416802": [1834, 0, 1774, "Reyes Moreno, Marco Antonio"], "6414087": [0, 0, 0, "Reyes Perdomo, Marcos"], "6416861": [1962, 2052, 2124, "Reyes Perez, Eury Luis"], "6412378": [0, 0, 1984, "Reyes Sosa, Rafael Ramon"], "6415342": [0, 0, 1794, "Reyes Vargas, Camilo"], "6414451": [0, 0, 0, "Reyes, Dabel"], "6412432": [0, 0, 0, "Reyes, Santo A"], "6414460": [2039, 0, 2070, "Reynoso Henriquez, Juan Bautista"], "6418597": [1845, 0, 0, "Rincon De Los Santos, Rony Azael"], "6419011": [0, 0, 0, "Rivas Cruz , Osbranyi De Jesus"], "6415350": [0, 0, 0, "Rivas Reynoso, Isidro"], "6411983": [0, 0, 0, "Rivas Sanz, Andry"], "6418112": [0, 0, 0, "Rivas, Carlos Genin"], "6418120": [0, 0, 0, "Rivera Colon, Ramon Emilio"], "6411410": [0, 0, 0, "Rivera, Delvy"], "6413277": [0, 0, 0, "Roa, Romulos"], "6410081": [1873, 0, 1795, "Robineau Germosen,Abel Taino"], "6419020": [0, 0, 0, "Robles , Elvis"], "6419038": [0, 0, 0, "Robles, Javier"], "6415458": [0, 0, 0, "Rocha, Gerson"], "6414753": [0, 0, 0, "Rodiguez, Leury"], "6419240": [0, 0, 0, "Rodriguez , Eliot"], "6418872": [1871, 0, 0, "Rodriguez Almanzar, Johan Amado"], "6412904": [0, 0, 0, "Rodriguez Dominguez, Jobel"], "6412149": [1775, 0, 1779, "Rodriguez Espaillat, Escarlet M."], "6416985": [0, 0, 1755, "Rodriguez Espaillat, Michael E."], "6417264": [0, 0, 0, "Rodriguez Fermin, Paul Dario"], "6417493": [0, 0, 0, "Rodriguez Franco, Carlos"], "6416101": [0, 0, 0, "Rodriguez Gomez, Lewis Dario"], "6412637": [0, 0, 0, "Rodriguez Gonzalez, Francisco"], "6413471": [0, 0, 0, "Rodriguez Hernandez, Luis Albert"], "6416535": [0, 0, 0, "Rodriguez Labrador, Irina"], "6419712": [1997, 2036, 2075, "Rodriguez Mejia, Eddy Gabriel"], "6412009": [0, 0, 0, "Rodriguez Morales, Jose Raul"], "6410308": [1886, 0, 1902, "Rodriguez Ramirez, Wilfredo"], "6411991": [0, 0, 0, "Rodriguez Sosa, Lisael"], "6417272": [0, 0, 0, "Rodriguez, Alexander NO"], "6410782": [0, 0, 0, "Rodriguez, Angel NA"], "6415083": [0, 0, 0, "Rodriguez, Angel NO"], "6418465": [0, 0, 0, "Rodriguez, Domingo Bartolo"], "6410316": [0, 0, 0, "Rodriguez, Eriberto"], "6410324": [1941, 0, 1944, "Rodriguez, Franyeline Antonio"], "6418368": [0, 0, 0, "Rodriguez, Gissel"], "6411428": [0, 0, 0, "Rodriguez, Johan P"], "6414915": [0, 0, 0, "Rodriguez, Jose Agustin"], "6412742": [0, 0, 0, "Rodriguez, Leonard"], "6413846": [0, 0, 0, "Rodriguez, Luis name match"], "6418139": [0, 0, 0, "Rodriguez, Manuel Maria"], "6417280": [0, 0, 0, "Rodriguez, Marvin"], "6417299": [0, 0, 0, "Rodriguez, Mauricio"], "6419046": [0, 0, 0, "Rodriguez, Rigoberto"], "6410154": [0, 0, 1941, "Rodriguez, Vidal T."], "6410936": [0, 0, 0, "Rodriguez, Wilfredo P"], "6414478": [0, 0, 0, "Rodriguz Tejada, Jairo"], "6411436": [0, 0, 0, "Rojas Tejada, Eligio"], "6415091": [0, 0, 0, "Rojas, Ana"], "641707": [1989, 0, 1814, "Rollier, Eric"], "6419658": [0, 0, 0, "Roman Hubieres, Yendri Mauricio"], "641065": [1972, 0, 1965, "Roncin, Cesar"], "6410006": [1795, 0, 1932, "Rondon Mota, Abraham"], "6413285": [0, 0, 0, "Roperto Logrono, Felix Valentin"], "6410758": [0, 0, 0, "Roque, Fernandez"], "6410642": [0, 0, 0, "Rosa Terrero, Dauris"], "6414486": [0, 0, 1881, "Rosado Paula, Felix"], "6413293": [0, 0, 0, "Rosario Diaz, Edward Antonio"], "6410944": [0, 0, 0, "Rosario Javier, Jesus Maria"], "6413307": [1845, 0, 1903, "Rosario Tejada, Angel Jose"], "6415059": [0, 0, 0, "Rosario, Erinson"], "6413854": [0, 0, 0, "Rosario, Haisy"], "6413862": [0, 0, 0, "Rosario, Jose Ant."], "6413994": [1839, 0, 0, "Rosario, Juan Carlos"], "6413870": [0, 0, 0, "Rosario, Victor"], "6416462": [0, 0, 0, "Roso Alcantara, Amauris"], "6417590": [0, 0, 0, "Rudenko, Roman"], "641073": [1771, 0, 0, "Ruelle, Cedric"], "6411614": [0, 0, 0, "Ruiz Hernandez, Francis Joel"], "6416675": [1928, 0, 1904, "Ruiz Pimentel, Oscar De Jesus"], "6415369": [0, 0, 0, "Ruiz Ramos, Richard"], "6410952": [0, 0, 0, "Ruiz, Richard P"], "641715": [1790, 1829, 1797, "Sabban, Manuel"], "6410960": [0, 0, 1652, "Salazar Ortiz, Edwin Ondino"], "6416357": [0, 0, 1898, "Salcedo, Cesar Estalin"], "6414001": [1959, 0, 1972, "Salcie, Francisco"], "6416365": [1870, 0, 0, "Saldivar, Roberto"], "6414109": [0, 0, 0, "Salvador, Miguel"], "6419518": [0, 0, 0, "Samsur, Alexis"], "6418473": [0, 0, 0, "Sanchez , Adalberto Antonio"], "6419780": [0, 0, 1821, "Sanchez , Jose Anibal"], "6411452": [1770, 1861, 1825, "Sanchez Acevedo, Jensy Manuel"], "6410014": [1873, 0, 1856, "Sanchez Mejia, Ery A."], "6419330": [1848, 0, 0, "Sanchez Minaya, Eduardo Manuel"], "6419933": [0, 0, 0, "Sanchez Mordan , Cristian"], "6410723": [0, 0, 0, "Sanchez Quezada, Jilsil Altagracia"], "6414117": [0, 0, 0, "Sanchez, Altagracia"], "6414494": [0, 0, 0, "Sanchez, Edwardo"], "6411746": [0, 0, 0, "Sanchez, Erick"], "6413560": [0, 0, 0, "Sanchez, J. Altagracia"], "6414273": [0, 0, 0, "Sanchez, Jesus"], "6415890": [0, 0, 1939, "Sanchez, Jose Anibal"], "6412769": [0, 0, 0, "Sanchez, Jose P."], "6418481": [0, 0, 0, "Santana Cadet, Jhonael"], "6418600": [0, 0, 0, "Santana Contrera, Hernan Junior"], "6412300": [0, 0, 0, "Santana Cueto, Juan Carlos"], "6412777": [0, 0, 0, "Santana Joesmel, Alberto"], "6419160": [0, 0, 0, "Santana Manzanillo, Julio Cesar"], "6419798": [0, 0, 1854, "Santana Martinez, Alberto Francisco"], "6412319": [0, 0, 1956, "Santana Palacio, Leonardo"], "6419313": [0, 0, 1804, "Santana, Humbertilio"], "6415709": [0, 0, 0, "Santana, Humbertillo"], "6415016": [1840, 0, 0, "Santana, Jeremi Saul"], "6414761": [0, 0, 0, "Santana, Manuel"], "6412785": [0, 0, 1915, "Santana, Osvaldo"], "6417035": [0, 0, 0, "Santiago , Darlenis"], "6417884": [1531, 1589, 1664, "Santiago Osorio, Estalyn"], "6417507": [0, 0, 0, "Santiago, Estalyn"], "6417302": [0, 0, 0, "Santiago, Estarlin"], "6416683": [0, 0, 0, "Santos Concepcion, Miguel Santos"], "6414508": [0, 0, 0, "Santos Reyes , Estarlin Javier"], "6415539": [0, 0, 1932, "Santos Rojas, Juan Abimelec"], "6418376": [0, 0, 0, "Santos S., Santa Modesta"], "6416691": [2014, 0, 1994, "Santos, Cristian"], "6415903": [0, 0, 1906, "Santos, Henry"], "6412793": [0, 0, 0, "Santos, Rafael"], "6419607": [1888, 1795, 1776, "Sarante Feliz, Genesis Melquisedec"], "641081": [1828, 0, 0, "Saurel, Frederic"], "641090": [1911, 0, 0, "Sauvage, Simon"], "6419941": [0, 0, 0, "Savinon , Nimay"], "641723": [1909, 0, 0, "Schaeffer, Vincent"], "6419178": [0, 0, 1901, "Schieck, Ralf"], "6417604": [0, 0, 0, "Sepulveda Rosario, Israel"], "6410979": [1699, 0, 0, "Sepulveda, Domingo Antonio"], "6411380": [0, 0, 1935, "Severino Peralta, Cesar Alexander"], "6414281": [0, 0, 1822, "Severino, Eliezer"], "6410669": [0, 0, 0, "Severino, Roberto"], "6417159": [0, 0, 2000, "Silva Archetti, Jose Rafael"], "6418384": [0, 0, 0, "Silva De Jsus, Paula"], "6412270": [0, 0, 0, "Silvestre, Melchor"], "6410677": [0, 0, 0, "Silvestrre, Melchor"], "6412327": [0, 0, 0, "Simoni, Roque"], "6410987": [0, 0, 0, "Solamo, Jhonatan"], "6416810": [0, 0, 0, "Solano Cuevas, Pedro"], "6416420": [0, 0, 0, "Solares Hernandez, Pedro Antonio"], "6418155": [0, 0, 0, "Solis P., Cebel Elias"], "6410332": [0, 0, 0, "Solis, Persio"], "6419542": [1945, 0, 1906, "Soriano Paulino, Junior Emmanuel"], "6415628": [0, 0, 1839, "Soriano, Leonel Gabriel"], "6410855": [0, 0, 0, "Sosa De La Rosa, Jose Andres"], "6412807": [1970, 1918, 2026, "Sosa Moran, Bryan Marc"], "6416225": [0, 0, 0, "Sosa, Ana Sarah"], "6411509": [0, 0, 1878, "Sosa, Johan Noel"], "6419054": [0, 0, 0, "Sosa, Soriano"], "6414770": [0, 0, 0, "Starlin, Robert"], "6412084": [0, 0, 0, "Sterling, Juan"], "6419526": [0, 0, 0, "Stevens, Tomas"], "6418619": [0, 0, 0, "Suarez De Los Santos, Abdon Isma"], "6418821": [0, 0, 0, "Suero Marte, Eusebio"], "6417418": [0, 0, 0, "Suero, Angel"], "6416373": [0, 0, 1758, "Suresa Camacho, Amauris"], "6417515": [1698, 0, 1831, "Tapia Nunez, Edwin Jared"], "6419267": [0, 0, 0, "Tapia Perez, Selinex Carolina"], "6412017": [0, 0, 0, "Tapia, Jeffry"], "6413480": [0, 0, 1846, "Tavarez Jimenez, Leandro"], "6415717": [0, 0, 0, "Taveras Betances, Francisco Argenis"], "6415997": [1709, 0, 0, "Taveras Rodriguez, Cristian Gabriel"], "6419720": [1823, 0, 1776, "Taveras Veras , Felix Miguel"], "6411460": [0, 0, 0, "Taveras, Ariel"], "6414516": [0, 0, 0, "Taveras, Starley"], "6411754": [0, 0, 0, "Taveras, Wilson"], "6417523": [0, 0, 0, "Tejada Fernandez, Alan"], "6410022": [0, 0, 0, "Then, Alexis"], "6410766": [0, 0, 0, "Then, Nicolas"], "6412076": [0, 0, 0, "Theogene, Carther"], "6410685": [1910, 1927, 1966, "Tiburcio Villar, Franklin Jonel"], "6411193": [1788, 1767, 1800, "Tiburcio Villar, Franky Samil"], "6410995": [1768, 0, 1875, "Tiburcio, Franklin Eddy"], "6411207": [0, 0, 0, "Tiburcio, Samuel"], "6418627": [1791, 0, 0, "Tineo Acosta, Junior Antonio"], "6416110": [2141, 0, 2007, "Tineo Rodriguez, Brian Jeremiah"], "6419062": [0, 0, 0, "Tineo, Juan Francisco"], "6416870": [1960, 1920, 1884, "Tolentino Mercedes, Argenis Johan"], "6415911": [0, 0, 0, "Toribio, Leonardo"], "6413030": [1943, 1928, 1946, "Torres Castro, Diomedes Cristino"], "6412475": [0, 0, 0, "Torres, Jorge"], "6418163": [0, 0, 0, "Torresdiaz, Rainiel"], "6417760": [0, 0, 0, "Trinidad Contreras , Dionicio"], "6418830": [0, 0, 0, "Trinidad Vasquez, Angel Luis"], "6415024": [0, 0, 0, "Trinidad, Gleider"], "6416829": [0, 0, 0, "Turbi Garcia, Samuel"], "6411622": [0, 0, 0, "Tyson, Cristian"], "6415377": [1905, 0, 1926, "Urena, Andoreny"], "6411215": [0, 0, 0, "Urena, Angel"], "6414788": [0, 0, 0, "Uribe, Benjamin"], "6415172": [0, 0, 1806, "Urraca, Gabriel"], "6414524": [0, 0, 0, "Uvinas Rodriguez, Carlos"], "6412874": [1978, 0, 0, "Valdespina Agramonte, Anthony Joasin"], "6411002": [1522, 0, 1702, "Valdez Cruz, Carlos Arturo"], "6410693": [0, 0, 0, "Valdez Ramirez, Jose Manuel"], "6416128": [1919, 0, 1940, "Valdez Soriano, Fidel Antonio"], "6418171": [0, 0, 0, "Valdez, Angel Mejia"], "6417426": [0, 0, 0, "Valdez, Marcos"], "6414800": [0, 0, 0, "Valdez, Zerik"], "6418848": [0, 0, 0, "Valentin Calderon, Lizandro Albe"], "6416136": [0, 0, 0, "Valenzuela Diaz, Yovanny De Jesu"], "6410030": [0, 0, 0, "Valenzuela, Dionisio"], "6410359": [0, 0, 0, "Vallejo, Erick"], "6413889": [0, 0, 0, "Valverde Aquino, Lenny Estiward"], "6416411": [0, 0, 1838, "Vargas Dujarric, Francisco Noel"], "6410707": [0, 1871, 1750, "Vargas, Hanoy"], "6413897": [0, 0, 0, "Vargas, Huascar"], "6410715": [0, 0, 0, "Vargas, Osvaldo"], "6410367": [1837, 0, 1858, "Vasquez Lorenzo, Carlos Alberto"], "6413048": [0, 0, 0, "Vasquez Sanchez, Junior"], "6412440": [0, 0, 0, "Vasquez Ventura, Luis Jose"], "6414818": [0, 0, 0, "Vasquez, Jose NOMBRE INCOMPLETO"], "6410049": [1885, 0, 0, "Vasquez, Junior"], "6410375": [1964, 0, 1941, "Vasquez, Sterling"], "6412025": [1778, 0, 1793, "Vazquez, Jesus Agustin"], "6418180": [0, 0, 0, "Vegoline Cuevas, Angel"], "6416446": [0, 0, 0, "Velez, Carlos Franco"], "6412815": [0, 0, 1758, "Velez, Enmanuel"], "6418392": [0, 0, 0, "Veloz, Jennifer"], "6417310": [1863, 0, 0, "Veloz, Reinaldo"], "6416837": [0, 0, 0, "Ventura Nunez, Yeudy"], "6416705": [1814, 0, 1838, "Ventura Ruiz, Francisco Alberto"], "6417779": [0, 0, 0, "Veras , Elsa Maria"], "6413315": [1938, 1903, 0, "Veras De Jesus, Randolf"], "6418880": [0, 0, 0, "Veras, Jose Antonio"], "6415792": [0, 0, 0, "Vialet Francisco, Robert"], "6412920": [0, 0, 0, "Vialet, Francisco"], "6411762": [0, 0, 0, "Vicioso, Stiven"], "6411770": [0, 0, 0, "Vicioso, Stiwar"], "6416233": [0, 0, 1807, "Victoriano Delgado, Juan Bautista"], "6417531": [0, 0, 1822, "Victoriano, Niman"], "6414826": [0, 0, 0, "Viloria, Jeymi"], "6417787": [0, 0, 0, "Vina Estrella, Dianelis"], "6417795": [0, 0, 0, "Vina Estrella, Yeremi"], "6417809": [0, 0, 0, "Vinas Nunez, Jose Heriberto"], "6419950": [0, 0, 1824, "Volquez Mejia, Ysrael Jose"], "641774": [1895, 1901, 0, "Wojtkowski, Frederic"], "641782": [1830, 0, 0, "Yvonne, Xavier"], "6412882": [1855, 0, 1864, "Zapata Robles, Jesus Elias"], "6417817": [0, 0, 0, "Zapata, Stephany NO"], "6415695": [0, 0, 0, "Zorrilla, Eddy"]}