{"914800": [1881, 1821, 0, "Aleksic, Branislav"], "914606": [2187, 2129, 2081, "Aleksic, Milan"], "914878": [2093, 0, 0, "Arsovic, Aleksandar"], "914126": [0, 0, 0, "Bosnjakovic, Lazar"], "914770": [1951, 2074, 2065, "Bozanic, Borivoje"], "914843": [2226, 2246, 2126, "Bujisic, Vlastimir"], "914320": [1647, 1811, 0, "Cejovic, Radisav"], "914339": [1844, 0, 0, "Cicarevic, Dimitrije"], "914916": [1959, 2031, 1851, "Colic, Aleksandar"], "914029": [2315, 2243, 2197, "Desnica, Vladan"], "914193": [2076, 2053, 2086, "Dimitrijevic, Dusan"], "914819": [1938, 0, 0, "Dinic, Milorad"], "914207": [1869, 1814, 0, "Djokic, Dusan"], "914240": [2199, 2269, 2354, "Djordjevic, Nebojsa"], "914789": [1982, 1967, 0, "Djordjevic, Radule"], "914436": [2176, 2187, 2203, "Djuric, Zoran"], "914614": [0, 0, 0, "Drobnjak, Milan"], "914037": [2021, 2144, 2087, "Dronjic, Sinisa"], "914622": [2213, 2214, 0, "Ducic, Branko"], "914347": [1771, 0, 0, "Gluscevic, Mira"], "914940": [0, 0, 0, "Golubovic, Manojlo"], "914924": [2173, 2133, 2113, "Grubisic, Zoran"], "914797": [2090, 0, 0, "Ignjatovic, Miroslav K"], "914886": [2197, 0, 0, "Jojic, Mihailo"], "914223": [2221, 2155, 0, "Jovanovic, Bojan V"], "914053": [1929, 1944, 0, "Jovanovic, Momir A"], "914576": [2136, 0, 0, "Jovanovic, Srdjan"], "914657": [1993, 2115, 2114, "Jovicic, Radosav"], "914185": [1958, 1968, 0, "Kecskemeti, Krisztina"], "914215": [1947, 2016, 1930, "Kostic, Aleksandar"], "914258": [2039, 2116, 2047, "Kostic, Stefan"], "914355": [0, 0, 0, "Krstic, Mladen G"], "914061": [1906, 2017, 1968, "Labus, Vladislav"], "914630": [1999, 1997, 1980, "Lazic, Dragan"], "914274": [2095, 0, 1927, "Lazic, Vladislav"], "914550": [0, 0, 0, "Lukic, Marija"], "914070": [1956, 0, 1989, "Mandic, Borislav"], "914665": [2136, 2143, 2114, "Marcak, Dejan"], "914681": [0, 0, 0, "Matic, Goran"], "914398": [0, 0, 0, "Micovic, Marko"], "914495": [2219, 2191, 2159, "Mihalj, Miroslav M"], "914711": [0, 0, 0, "Milenkovic, Dragan"], "914282": [0, 0, 0, "Mitic, Jovan S"], "914410": [1940, 0, 1963, "Mitrovic, Goran"], "914428": [2008, 0, 0, "Moskovljevic, Milan"], "914452": [1812, 0, 0, "Moskovljevic, Milica"], "914134": [1803, 0, 1773, "Nedeljkovic, Stanislava"], "914460": [1659, 0, 0, "Nedic, Andrijana"], "914967": [2219, 0, 0, "Nikolic, Radisa D"], "914827": [0, 0, 0, "Novcic, Nikola"], "914088": [1947, 0, 0, "Opalic, Aleksandar"], "914142": [1763, 0, 0, "Osap, Nikola"], "914835": [0, 0, 0, "Pantic, Dragan"], "914096": [1942, 1986, 0, "Pejic, Milos"], "914100": [1829, 1911, 0, "Pejic, Radoslav"], "914851": [0, 0, 0, "Peric, Marko"], "914479": [0, 0, 0, "Petrovic, Aleksandar B"], "914150": [1936, 1974, 1989, "Petrovic, Danijela"], "914487": [0, 0, 0, "Petrovic, Lazar I"], "914118": [1785, 1796, 1773, "Petrovic, Tatjana"], "914509": [0, 0, 0, "Petrovic, Zvonko"], "914754": [1836, 1832, 1814, "Prijovic, Miroslav"], "914363": [2002, 2069, 2063, "Pucarevic, Milenko"], "914975": [0, 0, 0, "Radovanovic, Slobodan"], "914568": [0, 0, 0, "Radunovic, Ivana"], "914720": [2145, 0, 0, "Rasic, Darko"], "914517": [2438, 2475, 2441, "Ratkovic, Miloje"], "914525": [2501, 2428, 2381, "Ratkovic, Milovan"], "914533": [2223, 2107, 2022, "Ratkovic, Petar"], "914673": [2106, 2046, 0, "Ribac, Dragoljub"], "914290": [0, 0, 0, "Ristic, Dusan"], "914932": [2335, 2426, 2360, "Savanovic, Aleksandar"], "914304": [0, 0, 0, "Simic, Nikola"], "914231": [2247, 0, 0, "Sparic, Nebojsa"], "914401": [2087, 1957, 1896, "Srdic, Danilo"], "914541": [0, 0, 0, "Sretenovic, Aleksandar"], "914649": [2230, 0, 0, "Stankovac, Dusan"], "914738": [0, 0, 0, "Stanojevic, Nenad"], "914266": [2214, 0, 2043, "Stevanovic, Goran M"], "914690": [2019, 0, 0, "Tesic, Zoran"], "914703": [2148, 2079, 1914, "Tomanovic, Nikola"], "914444": [2068, 0, 0, "Tomasevic, Sasa"], "914002": [1815, 0, 1799, "Vilagos, Emil"], "914169": [1872, 1864, 0, "Vojvodic, Sanja"], "914592": [1996, 0, 0, "Vrankovic, Luka"], "914380": [2038, 2072, 2026, "Vreljanski, Dragomir"], "914312": [0, 0, 0, "Vukadinovic, Aljosa"], "914746": [2100, 0, 0, "Vukovic, Rajko"], "914860": [2293, 2069, 2145, "Vukovic, Vladan"], "914983": [2063, 1984, 2046, "Zecevic, Igor"], "914584": [1879, 1889, 0, "Zecevic, Snezana"], "914762": [1934, 0, 1942, "Zivkovic, Ivan R"], "914908": [0, 0, 0, "Zlatanovic, Slavisa"]}